[
  {
    "sub": "OfficeChairs",
    "query": "office chair",
    "title": "Mainstays Chair Uneven",
    "url": "https://www.reddit.com/r/OfficeChairs/comments/1ulwuxs/mainstays_chair_uneven/",
    "id": "t3_1ulwuxs"
  },
  {
    "sub": "OfficeChairs",
    "query": "herman miller",
    "title": "Embody vs Gaming Embody: shoulder/posture feel, which is more open?",
    "url": "https://www.reddit.com/r/OfficeChairs/comments/1ulvi01/embody_vs_gaming_embody_shoulderposture_feel/",
    "id": "t3_1ulvi01"
  },
  {
    "sub": "OfficeChairs",
    "query": "lumbar support",
    "title": "ProtoArc EC300 thoughts and review",
    "url": "https://www.reddit.com/r/OfficeChairs/comments/1ulrssi/protoarc_ec300_thoughts_and_review/",
    "id": "t3_1ulrssi"
  },
  {
    "sub": "OfficeChairs",
    "query": "herman miller",
    "title": "Looking for a chair in the EU (max 450\u20ac)",
    "url": "https://www.reddit.com/r/OfficeChairs/comments/1ulnpe2/looking_for_a_chair_in_the_eu_max_450/",
    "id": "t3_1ulnpe2"
  },
  {
    "sub": "OfficeChairs",
    "query": "office chair",
    "title": "Is it good?",
    "url": "https://www.reddit.com/r/OfficeChairs/comments/1ulmd0d/is_it_good/",
    "id": "t3_1ulmd0d"
  },
  {
    "sub": "OfficeChairs",
    "query": "office chair",
    "title": "Any redflags for this Leap V2?",
    "url": "https://www.reddit.com/r/OfficeChairs/comments/1ull7bq/any_redflags_for_this_leap_v2/",
    "id": "t3_1ull7bq"
  },
  {
    "sub": "OfficeChairs",
    "query": "desk chair",
    "title": "Looking for new desk chair",
    "url": "https://www.reddit.com/r/OfficeChairs/comments/1uljauq/looking_for_new_desk_chair/",
    "id": "t3_1uljauq"
  },
  {
    "sub": "OfficeChairs",
    "query": "steelcase",
    "title": "Need new chair for fully remote position",
    "url": "https://www.reddit.com/r/OfficeChairs/comments/1ulj6g9/need_new_chair_for_fully_remote_position/",
    "id": "t3_1ulj6g9"
  },
  {
    "sub": "OfficeChairs",
    "query": "steelcase",
    "title": "Sedia SteelCase Leap V2 Damage Chair",
    "url": "https://www.reddit.com/r/OfficeChairs/comments/1ulhika/sedia_steelcase_leap_v2_damage_chair/",
    "id": "t3_1ulhika"
  },
  {
    "sub": "OfficeChairs",
    "query": "lumbar support",
    "title": "Opinions on the interstuhl every 211",
    "url": "https://www.reddit.com/r/OfficeChairs/comments/1ulekse/opinions_on_the_interstuhl_every_211/",
    "id": "t3_1ulekse"
  },
  {
    "sub": "OfficeChairs",
    "query": "office chair",
    "title": "Help me with some recommendations for a new chair (188cm/6'2 and roughly 87kg/192lb, more in desc')",
    "url": "https://www.reddit.com/r/OfficeChairs/comments/1uld2pp/help_me_with_some_recommendations_for_a_new_chair/",
    "id": "t3_1uld2pp"
  },
  {
    "sub": "OfficeChairs",
    "query": "desk chair",
    "title": "Recommendations for petite woman",
    "url": "https://www.reddit.com/r/OfficeChairs/comments/1ul8xqm/recommendations_for_petite_woman/",
    "id": "t3_1ul8xqm"
  },
  {
    "sub": "OfficeChairs",
    "query": "steelcase",
    "title": "Steelcase Leap v2 recline crunch",
    "url": "https://www.reddit.com/r/OfficeChairs/comments/1ul6y5t/steelcase_leap_v2_recline_crunch/",
    "id": "t3_1ul6y5t"
  },
  {
    "sub": "OfficeChairs",
    "query": "posture",
    "title": "Am I better off with a firm chair or a soft one?",
    "url": "https://www.reddit.com/r/OfficeChairs/comments/1ul5yzx/am_i_better_off_with_a_firm_chair_or_a_soft_one/",
    "id": "t3_1ul5yzx"
  }
]